sigpro/__init__.py
sigpro/basic_primitives.py
sigpro/contributing.py
sigpro/contributing_primitive.py
sigpro/core.py
sigpro/demo.py
sigpro/pipeline.py
sigpro/primitive.py
sigpro/aggregations/__init__.py
sigpro/aggregations/amplitude/__init__.py
sigpro/aggregations/amplitude/statistical.py
sigpro/aggregations/frequency/__init__.py
sigpro/aggregations/frequency/band.py
sigpro/aggregations/frequency_time/__init__.py
sigpro/data/demo_timeseries.csv
sigpro/primitives/sigpro/SigPro.json
sigpro/primitives/sigpro/aggregations/amplitude/statistical/crest_factor.json
sigpro/primitives/sigpro/aggregations/amplitude/statistical/kurtosis.json
sigpro/primitives/sigpro/aggregations/amplitude/statistical/mean.json
sigpro/primitives/sigpro/aggregations/amplitude/statistical/rms.json
sigpro/primitives/sigpro/aggregations/amplitude/statistical/skew.json
sigpro/primitives/sigpro/aggregations/amplitude/statistical/std.json
sigpro/primitives/sigpro/aggregations/amplitude/statistical/var.json
sigpro/primitives/sigpro/aggregations/frequency/band/band_mean.json
sigpro/primitives/sigpro/aggregations/frequency/band/band_rms.json
sigpro/primitives/sigpro/transformations/amplitude/identity/identity.json
sigpro/primitives/sigpro/transformations/amplitude/spectrum/power_spectrum.json
sigpro/primitives/sigpro/transformations/frequency/band/frequency_band.json
sigpro/primitives/sigpro/transformations/frequency/fft/fft.json
sigpro/primitives/sigpro/transformations/frequency/fft/fft_real.json
sigpro/primitives/sigpro/transformations/frequency/fftfreq/fft_freq.json
sigpro/primitives/sigpro/transformations/frequency_time/stft/stft.json
sigpro/primitives/sigpro/transformations/frequency_time/stft/stft_real.json
sigpro/transformations/__init__.py
sigpro/transformations/amplitude/__init__.py
sigpro/transformations/amplitude/identity.py
sigpro/transformations/amplitude/spectrum.py
sigpro/transformations/frequency/__init__.py
sigpro/transformations/frequency/band.py
sigpro/transformations/frequency/fft.py
sigpro-0.3.0.dist-info/AUTHORS.rst
sigpro-0.3.0.dist-info/LICENSE
sigpro-0.3.0.dist-info/METADATA
sigpro-0.3.0.dist-info/WHEEL
sigpro-0.3.0.dist-info/entry_points.txt
sigpro-0.3.0.dist-info/top_level.txt
sigpro-0.3.0.dist-info/RECORD
