Metadata-Version: 2.1
Name: sigpro
Version: 0.3.0
Summary: Signal Processing Tools for Machine Learning
Home-page: https://github.com/sintel-dev/SigPro
Author: MIT Data To AI Lab
Author-email: dailabmit@gmail.com
License: MIT license
Keywords: sigpro signal processing tools machine learning
Classifier: Development Status :: 2 - Pre-Alpha
Classifier: Intended Audience :: Developers
Classifier: License :: OSI Approved :: MIT License
Classifier: Natural Language :: English
Classifier: Programming Language :: Python :: 3
Classifier: Programming Language :: Python :: 3.9
Classifier: Programming Language :: Python :: 3.10
Classifier: Programming Language :: Python :: 3.11
Classifier: Programming Language :: Python :: 3.12
Requires-Python: >=3.9,<3.13
License-File: LICENSE
License-File: AUTHORS.rst
Requires-Dist: mlblocks >=0.6.2
Requires-Dist: pandas >=1.5.3
Requires-Dist: numpy >=1.26.0
Requires-Dist: scipy >=1.11.3
Provides-Extra: dev
Requires-Dist: bumpversion <0.6,>=0.5.3 ; extra == 'dev'
Requires-Dist: pip >=9.0.1 ; extra == 'dev'
Requires-Dist: watchdog <0.11,>=0.8.3 ; extra == 'dev'
Requires-Dist: m2r <0.3,>=0.2.0 ; extra == 'dev'
Requires-Dist: Sphinx <3,>=1.7.1 ; extra == 'dev'
Requires-Dist: sphinx-rtd-theme <0.5,>=0.2.4 ; extra == 'dev'
Requires-Dist: autodocsumm >=0.1.10 ; extra == 'dev'
Requires-Dist: markupsafe <2.1.0 ; extra == 'dev'
Requires-Dist: Jinja2 <3.1,>=2 ; extra == 'dev'
Requires-Dist: alabaster <=0.7.12 ; extra == 'dev'
Requires-Dist: sphinxcontrib-applehelp <1.0.8 ; extra == 'dev'
Requires-Dist: sphinxcontrib-devhelp <1.0.6 ; extra == 'dev'
Requires-Dist: sphinxcontrib-htmlhelp <2.0.5 ; extra == 'dev'
Requires-Dist: sphinxcontrib-serializinghtml <1.1.10 ; extra == 'dev'
Requires-Dist: sphinxcontrib-qthelp <1.0.7 ; extra == 'dev'
Requires-Dist: flake8 <4,>=3.7.7 ; extra == 'dev'
Requires-Dist: flake8-absolute-import <2,>=1.0 ; extra == 'dev'
Requires-Dist: flake8-docstrings <2,>=1.5.0 ; extra == 'dev'
Requires-Dist: flake8-sfs <0.1,>=0.0.3 ; extra == 'dev'
Requires-Dist: isort <5,>=4.3.4 ; extra == 'dev'
Requires-Dist: pylint <3,>=2.5.3 ; extra == 'dev'
Requires-Dist: autoflake <2,>=1.1 ; extra == 'dev'
Requires-Dist: autopep8 <2,>=1.4.3 ; extra == 'dev'
Requires-Dist: twine <4,>=1.10.0 ; extra == 'dev'
Requires-Dist: wheel >=0.30.0 ; extra == 'dev'
Requires-Dist: coverage <6,>=4.5.1 ; extra == 'dev'
Requires-Dist: tox <4,>=2.9.1 ; extra == 'dev'
Requires-Dist: importlib-metadata <5 ; extra == 'dev'
Requires-Dist: mistune <2 ; extra == 'dev'
Requires-Dist: invoke ; extra == 'dev'
Requires-Dist: pytest >=7.2.2 ; extra == 'dev'
Requires-Dist: pytest-cov >=4.1.0 ; extra == 'dev'
Requires-Dist: jupyter <2,>=1.0.0 ; extra == 'dev'
Requires-Dist: rundoc <0.5,>=0.4.3 ; extra == 'dev'
Provides-Extra: test
Requires-Dist: pytest >=7.2.2 ; extra == 'test'
Requires-Dist: pytest-cov >=4.1.0 ; extra == 'test'
Requires-Dist: jupyter <2,>=1.0.0 ; extra == 'test'
Requires-Dist: rundoc <0.5,>=0.4.3 ; extra == 'test'
